fastapi_sa_query/__init__.py
fastapi_sa_query/filter.py
fastapi_sa_query/func.py
fastapi_sa_query/order.py
fastapi_sa_query/py.typed
fastapi_sa_query-0.1.0.dist-info/METADATA
fastapi_sa_query-0.1.0.dist-info/WHEEL
fastapi_sa_query-0.1.0.dist-info/licenses/LICENSE
fastapi_sa_query-0.1.0.dist-info/RECORD
