Metadata-Version: 2.4
Name: fastapi-sa-query
Version: 0.1.0
Summary: Dynamic query filters and ordering for FastAPI + SQLAlchemy
Project-URL: Homepage, https://github.com/timaakulich/fastapi-sa-query
Project-URL: Documentation, https://github.com/timaakulich/fastapi-sa-query/blob/master/README.md
Project-URL: Repository, https://github.com/timaakulich/fastapi-sa-query
Project-URL: Issues, https://github.com/timaakulich/fastapi-sa-query/issues
Author-email: Timophey Akulich <tima.akulich@gmail.com>
License-Expression: MIT
License-File: LICENSE
Keywords: api,fastapi,filter,orm,query,rest,sqlalchemy
Classifier: Development Status :: 4 - Beta
Classifier: Environment :: Web Environment
Classifier: Framework :: FastAPI
Classifier: Intended Audience :: Developers
Classifier: License :: OSI Approved :: MIT License
Classifier: Operating System :: OS Independent
Classifier: Programming Language :: Python :: 3
Classifier: Programming Language :: Python :: 3.10
Classifier: Programming Language :: Python :: 3.11
Classifier: Programming Language :: Python :: 3.12
Classifier: Programming Language :: Python :: 3.13
Classifier: Topic :: Internet :: WWW/HTTP :: HTTP Servers
Classifier: Topic :: Software Development :: Libraries :: Python Modules
Classifier: Typing :: Typed
Requires-Python: >=3.10
Requires-Dist: fastapi>=0.100.0
Requires-Dist: sqlalchemy>=2.0.0
Provides-Extra: dev
Requires-Dist: httpx>=0.27.0; extra == 'dev'
Requires-Dist: mypy>=1.10.0; extra == 'dev'
Requires-Dist: pytest>=8.0.0; extra == 'dev'
Requires-Dist: ruff>=0.4.0; extra == 'dev'
Requires-Dist: uvicorn>=0.30.0; extra == 'dev'
